nrel_nsrdb-4.1.2.dist-info/licenses/LICENSE
nsrdb/__init__.py
nsrdb/_version.py
nsrdb/cli.py
nsrdb/nsrdb.py
nsrdb/aggregation/__init__.py
nsrdb/aggregation/aggregation.py
nsrdb/albedo/README.rst
nsrdb/albedo/__init__.py
nsrdb/albedo/albedo.py
nsrdb/albedo/cli.py
nsrdb/albedo/ims.py
nsrdb/albedo/modis.py
nsrdb/albedo/modis_v6_download.py
nsrdb/albedo/temperature_model.py
nsrdb/all_sky/README.rst
nsrdb/all_sky/__init__.py
nsrdb/all_sky/all_sky.py
nsrdb/all_sky/utilities.py
nsrdb/blend/__init__.py
nsrdb/blend/blend.py
nsrdb/config/README.rst
nsrdb/config/__init__.py
nsrdb/config/create_configs.py
nsrdb/config/nsrdb_vars.csv
nsrdb/config/var_descriptions.csv
nsrdb/config/pipeline_legacy/README.md
nsrdb/config/pipeline_legacy/config_east_nsrdb.json
nsrdb/config/pipeline_legacy/config_east_pipeline.json
nsrdb/config/pipeline_legacy/config_west_conus_nsrdb.json
nsrdb/config/pipeline_legacy/config_west_conus_pipeline.json
nsrdb/config/pipeline_legacy/run.sh
nsrdb/config/pipeline_mlclouds/README.md
nsrdb/config/pipeline_mlclouds/config_conus_west_nsrdb.json
nsrdb/config/pipeline_mlclouds/config_conus_west_pipeline.json
nsrdb/config/pipeline_mlclouds/config_east_nsrdb.json
nsrdb/config/pipeline_mlclouds/config_east_pipeline.json
nsrdb/config/pipeline_mlclouds/run.sh
nsrdb/config/templates/config_nsrdb_post2017.json
nsrdb/config/templates/config_nsrdb_pre2018.json
nsrdb/config/templates/config_pipeline.json
nsrdb/data_model/README.rst
nsrdb/data_model/__init__.py
nsrdb/data_model/albedo.py
nsrdb/data_model/asymmetry.py
nsrdb/data_model/base_handler.py
nsrdb/data_model/clouds.py
nsrdb/data_model/data_model.py
nsrdb/data_model/gfs.py
nsrdb/data_model/maiac_aod.py
nsrdb/data_model/merra.py
nsrdb/data_model/nrel_data.py
nsrdb/data_model/solar_zenith_angle.py
nsrdb/data_model/variable_factory.py
nsrdb/data_model/data/Monthly_pixel_correction_MERRA2_AOD.txt
nsrdb/data_model/data/Monthly_pixel_correction_MERRA2_Alpha.txt
nsrdb/data_model/data/README.md
nsrdb/data_model/data/merra_grid_srtm_500m_stats.csv
nrel_nsrdb-4.1.2.dist-info/METADATA
nrel_nsrdb-4.1.2.dist-info/WHEEL
nrel_nsrdb-4.1.2.dist-info/top_level.txt
nrel_nsrdb-4.1.2.dist-info/RECORD
