Metadata-Version: 2.4
Name: NREL-nsrdb
Version: 4.1.2
Summary: National Solar Radiation Database (NSRDB) Software
Author-email: Brandon Benton <brandon.benton@nrel.gov>
License: BSD-3-Clause
Project-URL: homepage, https://github.com/NREL/nsrdb
Project-URL: documentation, https://nrel.github.io/nsrdb/
Project-URL: repository, https://github.com/NREL/nsrdb
Keywords: nsrdb,NREL
Classifier: Development Status :: 4 - Beta
Classifier: Intended Audience :: Science/Research
Classifier: License :: OSI Approved :: BSD License
Classifier: Natural Language :: English
Classifier: Programming Language :: Python :: 3.9
Classifier: Programming Language :: Python :: 3.10
Classifier: Programming Language :: Python :: 3.11
Requires-Python: >=3.9
License-File: LICENSE
Requires-Dist: netCDF4<1.7,>=1.6
Requires-Dist: matplotlib>=3.1
Requires-Dist: NREL-gaps>=0.6.0
Requires-Dist: NREL-cloud_fs>=0.0.8
Requires-Dist: NREL-farms>=1.0.6
Requires-Dist: scikit-learn>=1.0
Requires-Dist: NREL-rest2>=1.0.2
Requires-Dist: NREL-mlclouds>=0.0.5
Requires-Dist: dask>=2024.8.0
Provides-Extra: dev
Requires-Dist: build>=0.5; extra == "dev"
Requires-Dist: pre-commit; extra == "dev"
Requires-Dist: ruff>=0.5.0; extra == "dev"
Provides-Extra: doc
Requires-Dist: sphinx>=7.0; extra == "doc"
Requires-Dist: sphinx_rtd_theme>=2.0; extra == "doc"
Requires-Dist: sphinx-click>=4.0; extra == "doc"
Provides-Extra: test
Requires-Dist: pytest>=5.2; extra == "test"
Requires-Dist: pytest-env>=1.1.3; extra == "test"
Requires-Dist: pytest-cov>=5.0.0; extra == "test"
Dynamic: license-file
